大二下/数字逻辑/lab/实验三 时序电路设计/lab3_total/lab3/lab3.srcs/sources_1/new/zero_sequence_detector.v
`timescale 1ns / 1ps
//////////////////////////////////////////////////////////////////////////////////
// Company: 
// Engineer: 
// 
// Create Date: 2025/05/22 20:04:03
// Design Name: 
// Module Name: zero_sequence_detector
// Project Name: 
// Target Devices: 
// Tool Versions: 
// Description: 
// 
// Dependencies: 
// 
// Revision:
// Revision 0.01 - File Created
// Additional Comments:
// 
//////////////////////////////////////////////////////////////////////////////////


// 定义模块
module zero_sequence_detector (
    input wire clk,   // 时钟信号
    input wire rst,   // 复位信号，高电平有效
    input wire I,     // 输入信号
    output reg  O     // 输出信号
);

    // 定义状态，使用 parameter 关键字提高可读性
    parameter STATE_1      = 3'b000; // 对应没有0的状态
    parameter STATE_0      = 3'b001; // 对应1个0的状态
    parameter STATE_00     = 3'b011; // 对应2个0的状态
    parameter STATE_000    = 3'b010; // 对应3个0的状态
    parameter STATE_0000_PLUS = 3'b100; // 对应4个及以上个0的状态

    // 声明状态寄存器和下一状态线
    reg [2:0] current_state; // 当前状态
    reg [2:0] next_state;    // 计算出的下一状态

    // =====================================================================
    // 时序逻辑：状态寄存器的更新
    // 在时钟上升沿或复位信号上升沿触发
    // =====================================================================
    always @(posedge clk or posedge rst) begin
        if (rst) begin
            // 复位时，回到初始状态
            current_state <= STATE_1;
        end else begin
            // 非复位时，在时钟上升沿更新当前状态为下一状态
            current_state <= next_state;
        end
    end

    // =====================================================================
    // 组合逻辑：计算下一状态
    // 根据当前状态和输入信号，计算下一个状态
    // 使用 case 语句描述状态转移表
    // =====================================================================
    always @(*) begin
        // 默认下一状态保持当前状态 (可选，但有助于处理未指定的情况)
        next_state = current_state; // 默认值，将在 case 语句中覆盖

        case (current_state)
            STATE_1: begin
                if (I == 0) begin
                    next_state = STATE_0;
                end else begin // I == 1
                    next_state = STATE_1;
                end
            end

            STATE_0: begin
                if (I == 0) begin
                    next_state = STATE_00;
                end else begin // I == 1
                    next_state = STATE_1;
                end
            end

            STATE_00: begin
                if (I == 0) begin
                    next_state = STATE_000;
                end else begin // I == 1
                    next_state = STATE_1;
                end
            end

            STATE_000: begin
                if (I == 0) begin
                    next_state = STATE_0000_PLUS;
                end else begin // I == 1
                    next_state = STATE_1;
                end
            end

            STATE_0000_PLUS: begin
                if (I == 0) begin
                    next_state = STATE_0000_PLUS; // 保持在结束状态
                end else begin // I == 1
                    next_state = STATE_1;
                end
            end

            // 处理无效状态编码 (通常不需要显式写出，综合工具会根据需求处理，
            // 但为了完整性，可以指定无效状态的转移，例如回到初始状态)
            default: begin
                next_state = STATE_1; // 无效状态转移到初始状态
            end
        endcase
    end

    // =====================================================================
    // 组合逻辑：计算输出
    // 根据当前状态和输入信号，计算输出信号 O
    // =====================================================================
    always @(*) begin
        // 默认输出为 0
        O = 1'b0;

        // 根据状态和输入确定输出
        if (current_state == STATE_0000_PLUS && I == 0) begin
            O = 1'b1;
        end
        // 其他情况输出默认为 0
    end

endmodule

大二下/数字逻辑/lab/实验三 时序电路设计/lab3_total/lab3/lab3.srcs/sim_1/new/testbench.v
// TestBench for zero_sequence_detector

`timescale 1ns / 1ps // 定义仿真时间单位和精度

module zero_sequence_detector_tb;

    // 信号声明
    reg clk;
    reg rst;
    reg I;
    wire O;

    // 参数定义
    parameter PERIOD = 10; // 时钟周期 10ns (100MHz)

    // 待测试模块例化 (DUT)
    zero_sequence_detector dut (
        .clk(clk),
        .rst(rst),
        .I(I),
        .O(O)
    );

    // 时钟生成
    initial begin
        clk = 0;
        forever begin
            #(PERIOD / 2) clk = ~clk;
        end
    end

    // 激励生成
    initial begin
        // 打开波形文件
        $dumpfile("zero_sequence_detector.vcd");
        $dumpvars(0, zero_sequence_detector_tb);

        // 初始化输入信号
        I = 0;

        // 1. 进行复位
        rst = 1;
        #PERIOD; // 保持复位一个时钟周期
        rst = 0;
        #PERIOD; // 等待一个时钟周期，确保复位完成

        // 2. 模拟不同的输入序列

        $display("--- Starting Simulation ---");
        // 监控关键信号
        $monitor("Time=%0t, State=%b, rst=%b, I=%b, O=%b", $time, dut.current_state, rst, I, O);

        // 测试序列1: 0000 (应输出1)
        #PERIOD; I = 0; // 第一个0，状态应转到 001
        #PERIOD; I = 0; // 第二个0，状态应转到 011
        #PERIOD; I = 0; // 第三个0，状态应转到 010
        #PERIOD; I = 0; // 第四个0，状态应转到 100，输出应为1

        // 测试序列2: 1 (应复位状态到 000)
        #PERIOD; I = 1;

        // 测试序列3: 0010000 (测试复位和再次检测)
        #PERIOD; I = 0; // 001
        #PERIOD; I = 0; // 011
        #PERIOD; I = 1; // 1，复位到 000
        #PERIOD; I = 0; // 001
        #PERIOD; I = 0; // 011
        #PERIOD; I = 0; // 010
        #PERIOD; I = 0; // 100，输出应为1

        // 测试序列4: 保持在 0000+ 状态输入 0
        #PERIOD; I = 0; // 保持在 100，输出应为1

        // 测试序列5: 从 0000+ 状态输入 1
        #PERIOD; I = 1; // 复位到 000

        // 3. 结束仿真
        # (PERIOD * 5); // 再运行一段时间
        $display("--- Ending Simulation ---");
        $finish; // 结束仿真

    end

endmodule

大二下/数字逻辑/lab/实验三 时序电路设计/lab3_total/lab3/lab3.sim/sim_1/behav/xsim/zero_sequence_detector.vcd
$date
   Thu May 22 20:18:41 2025
$end
$version
  2019.2
$end
$timescale
  1ps
$end
$scope module zero_sequence_detector_tb $end
$var reg 1 ! clk $end
$var reg 1 " rst $end
$var reg 1 # I $end
$var wire 1 $ O $end
$var parameter 32 % PERIOD [31:0] $end
$scope module dut $end
$var wire 1 & clk $end
$var wire 1 ' rst $end
$var wire 1 ( I $end
$var reg 1 ) O $end
$var reg 3 * current_state [2:0] $end
$var reg 3 + next_state [2:0] $end
$var parameter 3 , STATE_1 [2:0] $end
$var parameter 3 - STATE_0 [2:0] $end
$var parameter 3 . STATE_00 [2:0] $end
$var parameter 3 / STATE_000 [2:0] $end
$var parameter 3 0 STATE_0000_PLUS [2:0] $end
$upscope $end
$upscope $end
$enddefinitions $end
#0
$dumpvars
0!
1"
0#
0$
b1010 %
0&
1'
0(
0)
b0 *
b1 +
b0 ,
b1 -
b11 .
b10 /
b100 0
$end
#5000
1!
1&
#10000
0!
0"
0&
0'
#15000
1!
1&
0)
b1 *
b11 +
#20000
0!
0&
#25000
1!
1&
0)
b11 *
b10 +
#30000
0!
0&
#35000
1!
1&
0)
b10 *
b100 +
#40000
0!
0&
#45000
1!
1$
1&
1)
b100 *
#50000
0!
0&
#55000
1!
1&
#60000
0!
0&
#65000
1!
1&
#70000
0!
1#
0$
0&
1(
0)
b0 +
#75000
1!
1&
0)
b0 *
#80000
0!
0#
0&
0(
0)
b1 +
#85000
1!
1&
0)
b1 *
b11 +
#90000
0!
0&
#95000
1!
1&
0)
b11 *
b10 +
#100000
0!
1#
0&
1(
0)
b0 +
#105000
1!
1&
0)
b0 *
#110000
0!
0#
0&
0(
0)
b1 +
#115000
1!
1&
0)
b1 *
b11 +
#120000
0!
0&
#125000
1!
1&
0)
b11 *
b10 +
#130000
0!
0&
#135000
1!
1&
0)
b10 *
b100 +
#140000
0!
0&
#145000
1!
1$
1&
1)
b100 *
#150000
0!
0&
#155000
1!
1&
#160000
0!
1#
0$
0&
1(
0)
b0 +
#165000
1!
1&
0)
b0 *
